uzbminecraft/__init__.py
uzcraft-0.2.dist-info/METADATA
uzcraft-0.2.dist-info/WHEEL
uzcraft-0.2.dist-info/top_level.txt
uzcraft-0.2.dist-info/RECORD
