Metadata-Version: 2.1
Name: uzcraft
Version: 0.2
Summary: free 3d minecraft
Author: EsanbekovSalohiddin
Author-email: salohiddinsalohiddin345@gmail.com
Classifier: Programming Language :: Python :: 3
Classifier: License :: OSI Approved :: MIT License
Classifier: Operating System :: OS Independent
Requires-Dist: ursina
